<?xml version="1.0" encoding="UTF-8"?>
<objects serializationModel="Studio.02.02.00">
	<object class="AudioFile" id="{7967aa0c-1a55-4ad4-815a-3cc589e67ef3}">
		<property name="assetPath">
			<value>Fire, Whoosh, Swoosh, Burst, Sizzling x4 SND43342.wav</value>
		</property>
		<property name="frequencyInKHz">
			<value>96</value>
		</property>
		<property name="channelCount">
			<value>2</value>
		</property>
		<property name="length">
			<value>1.2810208333333333</value>
		</property>
		<relationship name="masterAssetFolder">
			<destination>{fc280779-9892-4e2e-94d3-0a93d66a2df7}</destination>
		</relationship>
	</object>
</objects>
